README.md
setup.py
zamia_prolog.egg-info/PKG-INFO
zamia_prolog.egg-info/SOURCES.txt
zamia_prolog.egg-info/dependency_links.txt
zamia_prolog.egg-info/top_level.txt
zamiaprolog/__init__.py
zamiaprolog/builtins.py
zamiaprolog/errors.py
zamiaprolog/logic.py
zamiaprolog/logicdb.py
zamiaprolog/model.py
zamiaprolog/parser.py
zamiaprolog/runtime.py