Metadata-Version: 1.1
Name: zamia-prolog
Version: 0.1.0
Summary: Embeddable Prolog dialect implemented in pure Python. Stores its knowlegdebase using SQLAlchemy for scalability.
Home-page: https://github.com/gooofy/zamia-prolog
Author: Guenter Bartsch
Author-email: guenter@zamia.org
License: LGPLv3
Platform: Linux
Classifier: Topic :: Software Development :: Interpreters
Classifier: Topic :: Software Development :: Compilers
Classifier: Intended Audience :: Developers
Classifier: Operating System :: POSIX :: Linux
Classifier: License :: OSI Approved :: GNU Lesser General Public License v3 (LGPLv3)
Classifier: Programming Language :: Python :: 2
Classifier: Programming Language :: Python :: 2.7
Classifier: Programming Language :: Python :: 3
Classifier: Programming Language :: Python :: 3.4
Classifier: Programming Language :: Prolog
